.DS_Store
nn_wien2k/__init__.py
nn_wien2k/nn_wien2k/__init__.py
nn_wien2k/nn_wien2k/first_neighborns.py
nn_wien2k-1.3.dist-info/METADATA
nn_wien2k-1.3.dist-info/WHEEL
nn_wien2k-1.3.dist-info/top_level.txt
nn_wien2k-1.3.dist-info/RECORD
