Metadata-Version: 2.1
Name: nn-wien2k
Version: 1.3
Summary: Библиотека для подсчета ближайших соседей атомов wien2k
Home-page: UNKNOWN
License: UNKNOWN
Platform: UNKNOWN
